sportswrangler/__init__.py
sportswrangler/fantasy/__init__.py
sportswrangler/fantasy/fantasydata/__init__.py
sportswrangler/fantasy/fantasydata/wrangler.py
sportswrangler/fantasy/ktc/__init__.py
sportswrangler/fantasy/ktc/wrangler.py
sportswrangler/generic/__init__.py
sportswrangler/generic/wrangler.py
sportswrangler/global_configs.py
sportswrangler/odds/__init__.py
sportswrangler/odds/the_odds_api/__init__.py
sportswrangler/odds/the_odds_api/utils/__init__.py
sportswrangler/odds/the_odds_api/utils/classes.py
sportswrangler/odds/the_odds_api/utils/constants.py
sportswrangler/odds/the_odds_api/utils/enums.py
sportswrangler/odds/the_odds_api/wranglers/__init__.py
sportswrangler/odds/the_odds_api/wranglers/base.py
sportswrangler/odds/the_odds_api/wranglers/epl.py
sportswrangler/odds/the_odds_api/wranglers/mlb.py
sportswrangler/odds/the_odds_api/wranglers/nba.py
sportswrangler/odds/the_odds_api/wranglers/ncaaf.py
sportswrangler/odds/the_odds_api/wranglers/nfl.py
sportswrangler/odds/the_odds_api/wranglers/nhl.py
sportswrangler/odds/the_odds_api/wranglers/wnba.py
sportswrangler/sports/__init__.py
sportswrangler/sports/data_feeds/__init__.py
sportswrangler/sports/data_feeds/assets/MLB/players.csv
sportswrangler/sports/data_feeds/assets/MLB/teams.csv
sportswrangler/sports/data_feeds/assets/NBA/players.csv
sportswrangler/sports/data_feeds/assets/NBA/teams.csv
sportswrangler/sports/data_feeds/assets/NFL/players.csv
sportswrangler/sports/data_feeds/assets/NFL/teams.csv
sportswrangler/sports/data_feeds/assets/NHL/players.csv
sportswrangler/sports/data_feeds/assets/NHL/teams.csv
sportswrangler/sports/data_feeds/wrangler.py
sportswrangler/sports/rotowire/__init__.py
sportswrangler/sports/rotowire/utils/__init__.py
sportswrangler/sports/rotowire/utils/constants.py
sportswrangler/sports/rotowire/wranglers/__init__.py
sportswrangler/sports/rotowire/wranglers/base.py
sportswrangler/sports/rotowire/wranglers/nfl.py
sportswrangler/utils/__init__.py
sportswrangler/utils/enums.py
sportswrangler-0.7.1.dist-info/METADATA
sportswrangler-0.7.1.dist-info/WHEEL
sportswrangler-0.7.1.dist-info/RECORD
