Metadata-Version: 2.1
Name: sportswrangler
Version: 0.7.1
Summary: Python package for wranglin' sports and sports odds data
Author: Dejon
Author-email: dejon.wright@gmail.com
Requires-Python: >=3.12,<4.0
Classifier: Programming Language :: Python :: 3
Classifier: Programming Language :: Python :: 3.12
Requires-Dist: bs4 (>=0.0.2,<0.0.3)
Requires-Dist: pandas (>=2.2.3,<3.0.0)
Requires-Dist: polars (>=1.30.0,<2.0.0)
Requires-Dist: pydantic (>=2.11.5,<3.0.0)
Requires-Dist: pytest (>=8.3.5,<9.0.0)
Requires-Dist: requests (>=2.32.3,<3.0.0)
